get_rolling_window/__init__.py
get_rolling_window-1.0.0.dist-info/LICENSE
get_rolling_window-1.0.0.dist-info/METADATA
get_rolling_window-1.0.0.dist-info/WHEEL
get_rolling_window-1.0.0.dist-info/top_level.txt
get_rolling_window-1.0.0.dist-info/RECORD
