Metadata-Version: 2.1
Name: get-rolling-window
Version: 1.0.0
Summary: Create a rolling window from a 1-D numpy ndarray
Home-page: https://github.com/kaelzhang/python-get-rolling-window
Author: kaelzhang
Author-email: 
License: MIT
Keywords: get-rolling-window
Platform: UNKNOWN
Classifier: Topic :: Software Development :: Libraries :: Python Modules
Classifier: Programming Language :: Python :: 3.7
Classifier: Programming Language :: Python :: 3.8
Classifier: Programming Language :: Python :: Implementation :: PyPy
Classifier: Topic :: Software Development :: Libraries :: Python Modules
Classifier: License :: OSI Approved :: MIT License
Requires-Python: >=3.7
Requires-Dist: numpy
